{"color": "#EFDECD", "createdAt" : ISODate("2015-07-06T07:50:33.059Z"), "updatedAt" : ISODate("2015-07-06T07:50:33.059Z"), "u_id": ObjectId("559a310dc73c5f5d1bfb7f91"), "__v" : 0}
{"color": "#CD9575", "createdAt" : ISODate("2015-07-06T07:50:33.059Z"), "updatedAt" : ISODate("2015-07-06T07:50:33.059Z"), "u_id": ObjectId("559a310dc73c5f5d1bfb7f91"), "__v" : 0}
{"color": "#FDD9B5", "createdAt" : ISODate("2015-07-06T07:50:33.059Z"), "updatedAt" : ISODate("2015-07-06T07:50:33.059Z"), "u_id": ObjectId("559a310dc73c5f5d1bfb7f91"), "__v" : 0}
{"color": "#78DBE2", "createdAt" : ISODate("2015-07-06T07:50:33.059Z"), "updatedAt" : ISODate("2015-07-06T07:50:33.059Z"), "u_id": ObjectId("559a310dc73c5f5d1bfb7f91"), "__v" : 0}
{"color": "#87A96B", "createdAt" : ISODate("2015-07-06T07:50:33.059Z"), "updatedAt" : ISODate("2015-07-06T07:50:33.059Z"), "u_id": ObjectId("559a310dc73c5f5d1bfb7f91"), "__v" : 0}
{"color": "#FFA474", "createdAt" : ISODate("2015-07-06T07:50:33.059Z"), "updatedAt" : ISODate("2015-07-06T07:50:33.059Z"), "u_id": ObjectId("559a310dc73c5f5d1bfb7f91"), "__v" : 0}
{"color": "#FAE7B5", "createdAt" : ISODate("2015-07-06T07:50:33.059Z"), "updatedAt" : ISODate("2015-07-06T07:50:33.059Z"), "u_id": ObjectId("559a310dc73c5f5d1bfb7f91"), "__v" : 0}
{"color": "#9F8170", "createdAt" : ISODate("2015-07-06T07:50:33.059Z"), "updatedAt" : ISODate("2015-07-06T07:50:33.059Z"), "u_id": ObjectId("559a310dc73c5f5d1bfb7f91"), "__v" : 0}
{"color": "#FD7C6E", "createdAt" : ISODate("2015-07-06T07:50:33.059Z"), "updatedAt" : ISODate("2015-07-06T07:50:33.059Z"), "u_id": ObjectId("559a310dc73c5f5d1bfb7f91"), "__v" : 0}
{"color": "#000000", "createdAt" : ISODate("2015-07-06T07:50:33.059Z"), "updatedAt" : ISODate("2015-07-06T07:50:33.059Z"), "u_id": ObjectId("559a310dc73c5f5d1bfb7f91"), "__v" : 0}
{"color": "#ACE5EE", "createdAt" : ISODate("2015-07-06T07:50:33.059Z"), "updatedAt" : ISODate("2015-07-06T07:50:33.059Z"), "u_id": ObjectId("559a310dc73c5f5d1bfb7f91"), "__v" : 0}
{"color": "#1F75FE", "createdAt" : ISODate("2015-07-06T07:50:33.059Z"), "updatedAt" : ISODate("2015-07-06T07:50:33.059Z"), "u_id": ObjectId("559a310dc73c5f5d1bfb7f91"), "__v" : 0}
{"color": "#A2A2D0", "createdAt" : ISODate("2015-07-06T07:50:33.059Z"), "updatedAt" : ISODate("2015-07-06T07:50:33.059Z"), "u_id": ObjectId("559a310dc73c5f5d1bfb7f91"), "__v" : 0}
{"color": "#6699CC", "createdAt" : ISODate("2015-07-06T07:50:33.059Z"), "updatedAt" : ISODate("2015-07-06T07:50:33.059Z"), "u_id": ObjectId("559a310dc73c5f5d1bfb7f91"), "__v" : 0}
{"color": "#0D98BA", "createdAt" : ISODate("2015-07-06T07:50:33.059Z"), "updatedAt" : ISODate("2015-07-06T07:50:33.059Z"), "u_id": ObjectId("559a310dc73c5f5d1bfb7f91"), "__v" : 0}
{"color": "#7366BD", "createdAt" : ISODate("2015-07-06T07:50:33.059Z"), "updatedAt" : ISODate("2015-07-06T07:50:33.059Z"), "u_id": ObjectId("559a310dc73c5f5d1bfb7f91"), "__v" : 0}
{"color": "#DE5D83", "createdAt" : ISODate("2015-07-06T07:50:33.059Z"), "updatedAt" : ISODate("2015-07-06T07:50:33.059Z"), "u_id": ObjectId("559a310dc73c5f5d1bfb7f91"), "__v" : 0}
{"color": "#CB4154", "createdAt" : ISODate("2015-07-06T07:50:33.059Z"), "updatedAt" : ISODate("2015-07-06T07:50:33.059Z"), "u_id": ObjectId("559a310dc73c5f5d1bfb7f91"), "__v" : 0}
{"color": "#B4674D", "createdAt" : ISODate("2015-07-06T07:50:33.059Z"), "updatedAt" : ISODate("2015-07-06T07:50:33.059Z"), "u_id": ObjectId("559a310dc73c5f5d1bfb7f91"), "__v" : 0}
{"color": "#FF7F49", "createdAt" : ISODate("2015-07-06T07:50:33.059Z"), "updatedAt" : ISODate("2015-07-06T07:50:33.059Z"), "u_id": ObjectId("559a310dc73c5f5d1bfb7f91"), "__v" : 0}
{"color": "#EA7E5D", "createdAt" : ISODate("2015-07-06T07:50:33.059Z"), "updatedAt" : ISODate("2015-07-06T07:50:33.059Z"), "u_id": ObjectId("559a310dc73c5f5d1bfb7f91"), "__v" : 0}
{"color": "#B0B7C6", "createdAt" : ISODate("2015-07-06T07:50:33.059Z"), "updatedAt" : ISODate("2015-07-06T07:50:33.059Z"), "u_id": ObjectId("559a310dc73c5f5d1bfb7f91"), "__v" : 0}
{"color": "#FFFF99", "createdAt" : ISODate("2015-07-06T07:50:33.059Z"), "updatedAt" : ISODate("2015-07-06T07:50:33.059Z"), "u_id": ObjectId("559a310dc73c5f5d1bfb7f91"), "__v" : 0}
{"color": "#1CD3A2", "createdAt" : ISODate("2015-07-06T07:50:33.059Z"), "updatedAt" : ISODate("2015-07-06T07:50:33.059Z"), "u_id": ObjectId("559a310dc73c5f5d1bfb7f91"), "__v" : 0}
{"color": "#FFAACC", "createdAt" : ISODate("2015-07-06T07:50:33.059Z"), "updatedAt" : ISODate("2015-07-06T07:50:33.059Z"), "u_id": ObjectId("559a310dc73c5f5d1bfb7f91"), "__v" : 0}
{"color": "#DD4492", "createdAt" : ISODate("2015-07-06T07:50:33.059Z"), "updatedAt" : ISODate("2015-07-06T07:50:33.059Z"), "u_id": ObjectId("559a310dc73c5f5d1bfb7f91"), "__v" : 0}
{"color": "#1DACD6", "createdAt" : ISODate("2015-07-06T07:50:33.059Z"), "updatedAt" : ISODate("2015-07-06T07:50:33.059Z"), "u_id": ObjectId("559a310dc73c5f5d1bfb7f91"), "__v" : 0}
{"color": "#BC5D58", "createdAt" : ISODate("2015-07-06T07:50:33.059Z"), "updatedAt" : ISODate("2015-07-06T07:50:33.059Z"), "u_id": ObjectId("559a310dc73c5f5d1bfb7f91"), "__v" : 0}
{"color": "#DD9475", "createdAt" : ISODate("2015-07-06T07:50:33.059Z"), "updatedAt" : ISODate("2015-07-06T07:50:33.059Z"), "u_id": ObjectId("559a310dc73c5f5d1bfb7f91"), "__v" : 0}
{"color": "#9ACEEB", "createdAt" : ISODate("2015-07-06T07:50:33.059Z"), "updatedAt" : ISODate("2015-07-06T07:50:33.059Z"), "u_id": ObjectId("559a310dc73c5f5d1bfb7f91"), "__v" : 0}
{"color": "#FFBCD9", "createdAt" : ISODate("2015-07-06T07:50:33.059Z"), "updatedAt" : ISODate("2015-07-06T07:50:33.059Z"), "u_id": ObjectId("559a310dc73c5f5d1bfb7f91"), "__v" : 0}
{"color": "#FDDB6D", "createdAt" : ISODate("2015-07-06T07:50:33.059Z"), "updatedAt" : ISODate("2015-07-06T07:50:33.059Z"), "u_id": ObjectId("559a310dc73c5f5d1bfb7f91"), "__v" : 0}
{"color": "#2B6CC4", "createdAt" : ISODate("2015-07-06T07:50:33.059Z"), "updatedAt" : ISODate("2015-07-06T07:50:33.059Z"), "u_id": ObjectId("559a310dc73c5f5d1bfb7f91"), "__v" : 0}
{"color": "#EFCDB8", "createdAt" : ISODate("2015-07-06T07:50:33.059Z"), "updatedAt" : ISODate("2015-07-06T07:50:33.059Z"), "u_id": ObjectId("559a310dc73c5f5d1bfb7f91"), "__v" : 0}
{"color": "#6E5160", "createdAt" : ISODate("2015-07-06T07:50:33.059Z"), "updatedAt" : ISODate("2015-07-06T07:50:33.059Z"), "u_id": ObjectId("559a310dc73c5f5d1bfb7f91"), "__v" : 0}
{"color": "#CEFF1D", "createdAt" : ISODate("2015-07-06T07:50:33.059Z"), "updatedAt" : ISODate("2015-07-06T07:50:33.059Z"), "u_id": ObjectId("559a310dc73c5f5d1bfb7f91"), "__v" : 0}
{"color": "#71BC78", "createdAt" : ISODate("2015-07-06T07:50:33.059Z"), "updatedAt" : ISODate("2015-07-06T07:50:33.059Z"), "u_id": ObjectId("559a310dc73c5f5d1bfb7f91"), "__v" : 0}
{"color": "#6DAE81", "createdAt" : ISODate("2015-07-06T07:50:33.059Z"), "updatedAt" : ISODate("2015-07-06T07:50:33.059Z"), "u_id": ObjectId("559a310dc73c5f5d1bfb7f91"), "__v" : 0}
{"color": "#C364C5", "createdAt" : ISODate("2015-07-06T07:50:33.059Z"), "updatedAt" : ISODate("2015-07-06T07:50:33.059Z"), "u_id": ObjectId("559a310dc73c5f5d1bfb7f91"), "__v" : 0}
{"color": "#CC6666", "createdAt" : ISODate("2015-07-06T07:50:33.059Z"), "updatedAt" : ISODate("2015-07-06T07:50:33.059Z"), "u_id": ObjectId("559a310dc73c5f5d1bfb7f91"), "__v" : 0}
{"color": "#E7C697", "createdAt" : ISODate("2015-07-06T07:50:33.059Z"), "updatedAt" : ISODate("2015-07-06T07:50:33.059Z"), "u_id": ObjectId("559a310dc73c5f5d1bfb7f91"), "__v" : 0}
{"color": "#FCD975", "createdAt" : ISODate("2015-07-06T07:50:33.059Z"), "updatedAt" : ISODate("2015-07-06T07:50:33.059Z"), "u_id": ObjectId("559a310dc73c5f5d1bfb7f91"), "__v" : 0}
{"color": "#A8E4A0", "createdAt" : ISODate("2015-07-06T07:50:33.059Z"), "updatedAt" : ISODate("2015-07-06T07:50:33.059Z"), "u_id": ObjectId("559a310dc73c5f5d1bfb7f91"), "__v" : 0}
{"color": "#95918C", "createdAt" : ISODate("2015-07-06T07:50:33.059Z"), "updatedAt" : ISODate("2015-07-06T07:50:33.059Z"), "u_id": ObjectId("559a310dc73c5f5d1bfb7f91"), "__v" : 0}
{"color": "#1CAC78", "createdAt" : ISODate("2015-07-06T07:50:33.059Z"), "updatedAt" : ISODate("2015-07-06T07:50:33.059Z"), "u_id": ObjectId("559a310dc73c5f5d1bfb7f91"), "__v" : 0}
{"color": "#1164B4", "createdAt" : ISODate("2015-07-06T07:50:33.059Z"), "updatedAt" : ISODate("2015-07-06T07:50:33.059Z"), "u_id": ObjectId("559a310dc73c5f5d1bfb7f91"), "__v" : 0}
{"color": "#F0E891", "createdAt" : ISODate("2015-07-06T07:50:33.059Z"), "updatedAt" : ISODate("2015-07-06T07:50:33.059Z"), "u_id": ObjectId("559a310dc73c5f5d1bfb7f91"), "__v" : 0}
{"color": "#FF1DCE", "createdAt" : ISODate("2015-07-06T07:50:33.059Z"), "updatedAt" : ISODate("2015-07-06T07:50:33.059Z"), "u_id": ObjectId("559a310dc73c5f5d1bfb7f91"), "__v" : 0}
{"color": "#B2EC5D", "createdAt" : ISODate("2015-07-06T07:50:33.059Z"), "updatedAt" : ISODate("2015-07-06T07:50:33.059Z"), "u_id": ObjectId("559a310dc73c5f5d1bfb7f91"), "__v" : 0}
{"color": "#5D76CB", "createdAt" : ISODate("2015-07-06T07:50:33.059Z"), "updatedAt" : ISODate("2015-07-06T07:50:33.059Z"), "u_id": ObjectId("559a310dc73c5f5d1bfb7f91"), "__v" : 0}
{"color": "#CA3767", "createdAt" : ISODate("2015-07-06T07:50:33.059Z"), "updatedAt" : ISODate("2015-07-06T07:50:33.059Z"), "u_id": ObjectId("559a310dc73c5f5d1bfb7f91"), "__v" : 0}
{"color": "#3BB08F", "createdAt" : ISODate("2015-07-06T07:50:33.059Z"), "updatedAt" : ISODate("2015-07-06T07:50:33.059Z"), "u_id": ObjectId("559a310dc73c5f5d1bfb7f91"), "__v" : 0}
{"color": "#FEFE22", "createdAt" : ISODate("2015-07-06T07:50:33.059Z"), "updatedAt" : ISODate("2015-07-06T07:50:33.059Z"), "u_id": ObjectId("559a310dc73c5f5d1bfb7f91"), "__v" : 0}
{"color": "#FCB4D5", "createdAt" : ISODate("2015-07-06T07:50:33.059Z"), "updatedAt" : ISODate("2015-07-06T07:50:33.059Z"), "u_id": ObjectId("559a310dc73c5f5d1bfb7f91"), "__v" : 0}
{"color": "#FFF44F", "createdAt" : ISODate("2015-07-06T07:50:33.059Z"), "updatedAt" : ISODate("2015-07-06T07:50:33.059Z"), "u_id": ObjectId("559a310dc73c5f5d1bfb7f91"), "__v" : 0}
{"color": "#FFBD88", "createdAt" : ISODate("2015-07-06T07:50:33.059Z"), "updatedAt" : ISODate("2015-07-06T07:50:33.059Z"), "u_id": ObjectId("559a310dc73c5f5d1bfb7f91"), "__v" : 0}
{"color": "#F664AF", "createdAt" : ISODate("2015-07-06T07:50:33.059Z"), "updatedAt" : ISODate("2015-07-06T07:50:33.059Z"), "u_id": ObjectId("559a310dc73c5f5d1bfb7f91"), "__v" : 0}
{"color": "#AAF0D1", "createdAt" : ISODate("2015-07-06T07:50:33.059Z"), "updatedAt" : ISODate("2015-07-06T07:50:33.059Z"), "u_id": ObjectId("559a310dc73c5f5d1bfb7f91"), "__v" : 0}
{"color": "#CD4A4C", "createdAt" : ISODate("2015-07-06T07:50:33.059Z"), "updatedAt" : ISODate("2015-07-06T07:50:33.059Z"), "u_id": ObjectId("559a310dc73c5f5d1bfb7f91"), "__v" : 0}
{"color": "#EDD19C", "createdAt" : ISODate("2015-07-06T07:50:33.059Z"), "updatedAt" : ISODate("2015-07-06T07:50:33.059Z"), "u_id": ObjectId("559a310dc73c5f5d1bfb7f91"), "__v" : 0}
{"color": "#979AAA", "createdAt" : ISODate("2015-07-06T07:50:33.059Z"), "updatedAt" : ISODate("2015-07-06T07:50:33.059Z"), "u_id": ObjectId("559a310dc73c5f5d1bfb7f91"), "__v" : 0}
{"color": "#FF8243", "createdAt" : ISODate("2015-07-06T07:50:33.059Z"), "updatedAt" : ISODate("2015-07-06T07:50:33.059Z"), "u_id": ObjectId("559a310dc73c5f5d1bfb7f91"), "__v" : 0}
{"color": "#C8385A", "createdAt" : ISODate("2015-07-06T07:50:33.059Z"), "updatedAt" : ISODate("2015-07-06T07:50:33.059Z"), "u_id": ObjectId("559a310dc73c5f5d1bfb7f91"), "__v" : 0}
{"color": "#EF98AA", "createdAt" : ISODate("2015-07-06T07:50:33.059Z"), "updatedAt" : ISODate("2015-07-06T07:50:33.059Z"), "u_id": ObjectId("559a310dc73c5f5d1bfb7f91"), "__v" : 0}
{"color": "#FDBCB4", "createdAt" : ISODate("2015-07-06T07:50:33.059Z"), "updatedAt" : ISODate("2015-07-06T07:50:33.059Z"), "u_id": ObjectId("559a310dc73c5f5d1bfb7f91"), "__v" : 0}
{"color": "#1A4876", "createdAt" : ISODate("2015-07-06T07:50:33.059Z"), "updatedAt" : ISODate("2015-07-06T07:50:33.059Z"), "u_id": ObjectId("559a310dc73c5f5d1bfb7f91"), "__v" : 0}
{"color": "#30BA8F", "createdAt" : ISODate("2015-07-06T07:50:33.059Z"), "updatedAt" : ISODate("2015-07-06T07:50:33.059Z"), "u_id": ObjectId("559a310dc73c5f5d1bfb7f91"), "__v" : 0}
{"color": "#C54B8C", "createdAt" : ISODate("2015-07-06T07:50:33.059Z"), "updatedAt" : ISODate("2015-07-06T07:50:33.059Z"), "u_id": ObjectId("559a310dc73c5f5d1bfb7f91"), "__v" : 0}
{"color": "#1974D2", "createdAt" : ISODate("2015-07-06T07:50:33.059Z"), "updatedAt" : ISODate("2015-07-06T07:50:33.059Z"), "u_id": ObjectId("559a310dc73c5f5d1bfb7f91"), "__v" : 0}
{"color": "#FFA343", "createdAt" : ISODate("2015-07-06T07:50:33.059Z"), "updatedAt" : ISODate("2015-07-06T07:50:33.059Z"), "u_id": ObjectId("559a310dc73c5f5d1bfb7f91"), "__v" : 0}
{"color": "#BAB86C", "createdAt" : ISODate("2015-07-06T07:50:33.059Z"), "updatedAt" : ISODate("2015-07-06T07:50:33.059Z"), "u_id": ObjectId("559a310dc73c5f5d1bfb7f91"), "__v" : 0}
{"color": "#FF7538", "createdAt" : ISODate("2015-07-06T07:50:33.059Z"), "updatedAt" : ISODate("2015-07-06T07:50:33.059Z"), "u_id": ObjectId("559a310dc73c5f5d1bfb7f91"), "__v" : 0}
{"color": "#FF2B2B", "createdAt" : ISODate("2015-07-06T07:50:33.059Z"), "updatedAt" : ISODate("2015-07-06T07:50:33.059Z"), "u_id": ObjectId("559a310dc73c5f5d1bfb7f91"), "__v" : 0}
{"color": "#F8D568", "createdAt" : ISODate("2015-07-06T07:50:33.059Z"), "updatedAt" : ISODate("2015-07-06T07:50:33.059Z"), "u_id": ObjectId("559a310dc73c5f5d1bfb7f91"), "__v" : 0}
{"color": "#E6A8D7", "createdAt" : ISODate("2015-07-06T07:50:33.059Z"), "updatedAt" : ISODate("2015-07-06T07:50:33.059Z"), "u_id": ObjectId("559a310dc73c5f5d1bfb7f91"), "__v" : 0}
{"color": "#414A4C", "createdAt" : ISODate("2015-07-06T07:50:33.059Z"), "updatedAt" : ISODate("2015-07-06T07:50:33.059Z"), "u_id": ObjectId("559a310dc73c5f5d1bfb7f91"), "__v" : 0}
{"color": "#FF6E4A", "createdAt" : ISODate("2015-07-06T07:50:33.059Z"), "updatedAt" : ISODate("2015-07-06T07:50:33.059Z"), "u_id": ObjectId("559a310dc73c5f5d1bfb7f91"), "__v" : 0}
{"color": "#1CA9C9", "createdAt" : ISODate("2015-07-06T07:50:33.059Z"), "updatedAt" : ISODate("2015-07-06T07:50:33.059Z"), "u_id": ObjectId("559a310dc73c5f5d1bfb7f91"), "__v" : 0}
{"color": "#FFCFAB", "createdAt" : ISODate("2015-07-06T07:50:33.059Z"), "updatedAt" : ISODate("2015-07-06T07:50:33.059Z"), "u_id": ObjectId("559a310dc73c5f5d1bfb7f91"), "__v" : 0}
{"color": "#C5D0E6", "createdAt" : ISODate("2015-07-06T07:50:33.059Z"), "updatedAt" : ISODate("2015-07-06T07:50:33.059Z"), "u_id": ObjectId("559a310dc73c5f5d1bfb7f91"), "__v" : 0}
{"color": "#FDDDE6", "createdAt" : ISODate("2015-07-06T07:50:33.059Z"), "updatedAt" : ISODate("2015-07-06T07:50:33.059Z"), "u_id": ObjectId("559a310dc73c5f5d1bfb7f91"), "__v" : 0}
{"color": "#158078", "createdAt" : ISODate("2015-07-06T07:50:33.059Z"), "updatedAt" : ISODate("2015-07-06T07:50:33.059Z"), "u_id": ObjectId("559a310dc73c5f5d1bfb7f91"), "__v" : 0}
{"color": "#FC74FD", "createdAt" : ISODate("2015-07-06T07:50:33.059Z"), "updatedAt" : ISODate("2015-07-06T07:50:33.059Z"), "u_id": ObjectId("559a310dc73c5f5d1bfb7f91"), "__v" : 0}
{"color": "#F78FA7", "createdAt" : ISODate("2015-07-06T07:50:33.059Z"), "updatedAt" : ISODate("2015-07-06T07:50:33.059Z"), "u_id": ObjectId("559a310dc73c5f5d1bfb7f91"), "__v" : 0}
{"color": "#8E4585", "createdAt" : ISODate("2015-07-06T07:50:33.059Z"), "updatedAt" : ISODate("2015-07-06T07:50:33.059Z"), "u_id": ObjectId("559a310dc73c5f5d1bfb7f91"), "__v" : 0}
{"color": "#7442C8", "createdAt" : ISODate("2015-07-06T07:50:33.059Z"), "updatedAt" : ISODate("2015-07-06T07:50:33.059Z"), "u_id": ObjectId("559a310dc73c5f5d1bfb7f91"), "__v" : 0}
{"color": "#9D81BA", "createdAt" : ISODate("2015-07-06T07:50:33.059Z"), "updatedAt" : ISODate("2015-07-06T07:50:33.059Z"), "u_id": ObjectId("559a310dc73c5f5d1bfb7f91"), "__v" : 0}
{"color": "#FE4EDA", "createdAt" : ISODate("2015-07-06T07:50:33.059Z"), "updatedAt" : ISODate("2015-07-06T07:50:33.059Z"), "u_id": ObjectId("559a310dc73c5f5d1bfb7f91"), "__v" : 0}
{"color": "#FF496C", "createdAt" : ISODate("2015-07-06T07:50:33.059Z"), "updatedAt" : ISODate("2015-07-06T07:50:33.059Z"), "u_id": ObjectId("559a310dc73c5f5d1bfb7f91"), "__v" : 0}
{"color": "#D68A59", "createdAt" : ISODate("2015-07-06T07:50:33.059Z"), "updatedAt" : ISODate("2015-07-06T07:50:33.059Z"), "u_id": ObjectId("559a310dc73c5f5d1bfb7f91"), "__v" : 0}
{"color": "#714B23", "createdAt" : ISODate("2015-07-06T07:50:33.059Z"), "updatedAt" : ISODate("2015-07-06T07:50:33.059Z"), "u_id": ObjectId("559a310dc73c5f5d1bfb7f91"), "__v" : 0}
{"color": "#FF48D0", "createdAt" : ISODate("2015-07-06T07:50:33.059Z"), "updatedAt" : ISODate("2015-07-06T07:50:33.059Z"), "u_id": ObjectId("559a310dc73c5f5d1bfb7f91"), "__v" : 0}
{"color": "#E3256B", "createdAt" : ISODate("2015-07-06T07:50:33.059Z"), "updatedAt" : ISODate("2015-07-06T07:50:33.059Z"), "u_id": ObjectId("559a310dc73c5f5d1bfb7f91"), "__v" : 0}
{"color": "#EE204D", "createdAt" : ISODate("2015-07-06T07:50:33.059Z"), "updatedAt" : ISODate("2015-07-06T07:50:33.059Z"), "u_id": ObjectId("559a310dc73c5f5d1bfb7f91"), "__v" : 0}
{"color": "#FF5349", "createdAt" : ISODate("2015-07-06T07:50:33.059Z"), "updatedAt" : ISODate("2015-07-06T07:50:33.059Z"), "u_id": ObjectId("559a310dc73c5f5d1bfb7f91"), "__v" : 0}
{"color": "#C0448F", "createdAt" : ISODate("2015-07-06T07:50:33.059Z"), "updatedAt" : ISODate("2015-07-06T07:50:33.059Z"), "u_id": ObjectId("559a310dc73c5f5d1bfb7f91"), "__v" : 0}
{"color": "#1FCECB", "createdAt" : ISODate("2015-07-06T07:50:33.059Z"), "updatedAt" : ISODate("2015-07-06T07:50:33.059Z"), "u_id": ObjectId("559a310dc73c5f5d1bfb7f91"), "__v" : 0}
{"color": "#7851A9", "createdAt" : ISODate("2015-07-06T07:50:33.059Z"), "updatedAt" : ISODate("2015-07-06T07:50:33.059Z"), "u_id": ObjectId("559a310dc73c5f5d1bfb7f91"), "__v" : 0}
{"color": "#FF9BAA", "createdAt" : ISODate("2015-07-06T07:50:33.059Z"), "updatedAt" : ISODate("2015-07-06T07:50:33.059Z"), "u_id": ObjectId("559a310dc73c5f5d1bfb7f91"), "__v" : 0}
{"color": "#FC2847", "createdAt" : ISODate("2015-07-06T07:50:33.059Z"), "updatedAt" : ISODate("2015-07-06T07:50:33.059Z"), "u_id": ObjectId("559a310dc73c5f5d1bfb7f91"), "__v" : 0}
{"color": "#76FF7A", "createdAt" : ISODate("2015-07-06T07:50:33.059Z"), "updatedAt" : ISODate("2015-07-06T07:50:33.059Z"), "u_id": ObjectId("559a310dc73c5f5d1bfb7f91"), "__v" : 0}
{"color": "#9FE2BF", "createdAt" : ISODate("2015-07-06T07:50:33.059Z"), "updatedAt" : ISODate("2015-07-06T07:50:33.059Z"), "u_id": ObjectId("559a310dc73c5f5d1bfb7f91"), "__v" : 0}
{"color": "#A5694F", "createdAt" : ISODate("2015-07-06T07:50:33.059Z"), "updatedAt" : ISODate("2015-07-06T07:50:33.059Z"), "u_id": ObjectId("559a310dc73c5f5d1bfb7f91"), "__v" : 0}
{"color": "#8A795D", "createdAt" : ISODate("2015-07-06T07:50:33.059Z"), "updatedAt" : ISODate("2015-07-06T07:50:33.059Z"), "u_id": ObjectId("559a310dc73c5f5d1bfb7f91"), "__v" : 0}
{"color": "#45CEA2", "createdAt" : ISODate("2015-07-06T07:50:33.059Z"), "updatedAt" : ISODate("2015-07-06T07:50:33.059Z"), "u_id": ObjectId("559a310dc73c5f5d1bfb7f91"), "__v" : 0}
{"color": "#FB7EFD", "createdAt" : ISODate("2015-07-06T07:50:33.059Z"), "updatedAt" : ISODate("2015-07-06T07:50:33.059Z"), "u_id": ObjectId("559a310dc73c5f5d1bfb7f91"), "__v" : 0}
{"color": "#CDC5C2", "createdAt" : ISODate("2015-07-06T07:50:33.059Z"), "updatedAt" : ISODate("2015-07-06T07:50:33.059Z"), "u_id": ObjectId("559a310dc73c5f5d1bfb7f91"), "__v" : 0}
{"color": "#80DAEB", "createdAt" : ISODate("2015-07-06T07:50:33.059Z"), "updatedAt" : ISODate("2015-07-06T07:50:33.059Z"), "u_id": ObjectId("559a310dc73c5f5d1bfb7f91"), "__v" : 0}
{"color": "#ECEABE", "createdAt" : ISODate("2015-07-06T07:50:33.059Z"), "updatedAt" : ISODate("2015-07-06T07:50:33.059Z"), "u_id": ObjectId("559a310dc73c5f5d1bfb7f91"), "__v" : 0}
{"color": "#FFCF48", "createdAt" : ISODate("2015-07-06T07:50:33.059Z"), "updatedAt" : ISODate("2015-07-06T07:50:33.059Z"), "u_id": ObjectId("559a310dc73c5f5d1bfb7f91"), "__v" : 0}
{"color": "#FD5E53", "createdAt" : ISODate("2015-07-06T07:50:33.059Z"), "updatedAt" : ISODate("2015-07-06T07:50:33.059Z"), "u_id": ObjectId("559a310dc73c5f5d1bfb7f91"), "__v" : 0}
{"color": "#FAA76C", "createdAt" : ISODate("2015-07-06T07:50:33.059Z"), "updatedAt" : ISODate("2015-07-06T07:50:33.059Z"), "u_id": ObjectId("559a310dc73c5f5d1bfb7f91"), "__v" : 0}
{"color": "#18A7B5", "createdAt" : ISODate("2015-07-06T07:50:33.059Z"), "updatedAt" : ISODate("2015-07-06T07:50:33.059Z"), "u_id": ObjectId("559a310dc73c5f5d1bfb7f91"), "__v" : 0}
{"color": "#EBC7DF", "createdAt" : ISODate("2015-07-06T07:50:33.059Z"), "updatedAt" : ISODate("2015-07-06T07:50:33.059Z"), "u_id": ObjectId("559a310dc73c5f5d1bfb7f91"), "__v" : 0}
{"color": "#FC89AC", "createdAt" : ISODate("2015-07-06T07:50:33.059Z"), "updatedAt" : ISODate("2015-07-06T07:50:33.059Z"), "u_id": ObjectId("559a310dc73c5f5d1bfb7f91"), "__v" : 0}
{"color": "#DBD7D2", "createdAt" : ISODate("2015-07-06T07:50:33.059Z"), "updatedAt" : ISODate("2015-07-06T07:50:33.059Z"), "u_id": ObjectId("559a310dc73c5f5d1bfb7f91"), "__v" : 0}
{"color": "#17806D", "createdAt" : ISODate("2015-07-06T07:50:33.059Z"), "updatedAt" : ISODate("2015-07-06T07:50:33.059Z"), "u_id": ObjectId("559a310dc73c5f5d1bfb7f91"), "__v" : 0}
{"color": "#DEAA88", "createdAt" : ISODate("2015-07-06T07:50:33.059Z"), "updatedAt" : ISODate("2015-07-06T07:50:33.059Z"), "u_id": ObjectId("559a310dc73c5f5d1bfb7f91"), "__v" : 0}
{"color": "#77DDE7", "createdAt" : ISODate("2015-07-06T07:50:33.059Z"), "updatedAt" : ISODate("2015-07-06T07:50:33.059Z"), "u_id": ObjectId("559a310dc73c5f5d1bfb7f91"), "__v" : 0}
{"color": "#FFFF66", "createdAt" : ISODate("2015-07-06T07:50:33.059Z"), "updatedAt" : ISODate("2015-07-06T07:50:33.059Z"), "u_id": ObjectId("559a310dc73c5f5d1bfb7f91"), "__v" : 0}
{"color": "#926EAE", "createdAt" : ISODate("2015-07-06T07:50:33.059Z"), "updatedAt" : ISODate("2015-07-06T07:50:33.059Z"), "u_id": ObjectId("559a310dc73c5f5d1bfb7f91"), "__v" : 0}
{"color": "#324AB2", "createdAt" : ISODate("2015-07-06T07:50:33.059Z"), "updatedAt" : ISODate("2015-07-06T07:50:33.059Z"), "u_id": ObjectId("559a310dc73c5f5d1bfb7f91"), "__v" : 0}
{"color": "#F75394", "createdAt" : ISODate("2015-07-06T07:50:33.059Z"), "updatedAt" : ISODate("2015-07-06T07:50:33.059Z"), "u_id": ObjectId("559a310dc73c5f5d1bfb7f91"), "__v" : 0}
{"color": "#FFA089", "createdAt" : ISODate("2015-07-06T07:50:33.059Z"), "updatedAt" : ISODate("2015-07-06T07:50:33.059Z"), "u_id": ObjectId("559a310dc73c5f5d1bfb7f91"), "__v" : 0}
{"color": "#8F509D", "createdAt" : ISODate("2015-07-06T07:50:33.059Z"), "updatedAt" : ISODate("2015-07-06T07:50:33.059Z"), "u_id": ObjectId("559a310dc73c5f5d1bfb7f91"), "__v" : 0}
{"color": "#FFFFFF", "createdAt" : ISODate("2015-07-06T07:50:33.059Z"), "updatedAt" : ISODate("2015-07-06T07:50:33.059Z"), "u_id": ObjectId("559a310dc73c5f5d1bfb7f91"), "__v" : 0}
{"color": "#A2ADD0", "createdAt" : ISODate("2015-07-06T07:50:33.059Z"), "updatedAt" : ISODate("2015-07-06T07:50:33.059Z"), "u_id": ObjectId("559a310dc73c5f5d1bfb7f91"), "__v" : 0}
{"color": "#FF43A4", "createdAt" : ISODate("2015-07-06T07:50:33.059Z"), "updatedAt" : ISODate("2015-07-06T07:50:33.059Z"), "u_id": ObjectId("559a310dc73c5f5d1bfb7f91"), "__v" : 0}
{"color": "#FC6C85", "createdAt" : ISODate("2015-07-06T07:50:33.059Z"), "updatedAt" : ISODate("2015-07-06T07:50:33.059Z"), "u_id": ObjectId("559a310dc73c5f5d1bfb7f91"), "__v" : 0}
{"color": "#CDA4DE", "createdAt" : ISODate("2015-07-06T07:50:33.059Z"), "updatedAt" : ISODate("2015-07-06T07:50:33.059Z"), "u_id": ObjectId("559a310dc73c5f5d1bfb7f91"), "__v" : 0}
{"color": "#FCE883", "createdAt" : ISODate("2015-07-06T07:50:33.059Z"), "updatedAt" : ISODate("2015-07-06T07:50:33.059Z"), "u_id": ObjectId("559a310dc73c5f5d1bfb7f91"), "__v" : 0}
{"color": "#C5E384", "createdAt" : ISODate("2015-07-06T07:50:33.059Z"), "updatedAt" : ISODate("2015-07-06T07:50:33.059Z"), "u_id": ObjectId("559a310dc73c5f5d1bfb7f91"), "__v" : 0} 
{"color": "#FFAE42", "createdAt" : ISODate("2015-07-06T07:50:33.059Z"), "updatedAt" : ISODate("2015-07-06T07:50:33.059Z"), "u_id": ObjectId("559a310dc73c5f5d1bfb7f91"), "__v" : 0}